README.md
setup.cfg
setup.py
supdoc/__init__.py
supdoc/__main__.py
supdoc/cache.py
supdoc/docs.py
supdoc/exc.py
supdoc/help.py
supdoc/inspector.py
supdoc/markdown_doctest.py
supdoc/modules.py
supdoc/objdoc.py
supdoc/parse.py
supdoc/path.py
supdoc/terminal.py
supdoc/test.py
supdoc.egg-info/PKG-INFO
supdoc.egg-info/SOURCES.txt
supdoc.egg-info/dependency_links.txt
supdoc.egg-info/entry_points.txt
supdoc.egg-info/requires.txt
supdoc.egg-info/top_level.txt
supdoc/html/__init__.py
supdoc/html/gen.py
supdoc/html/serve.py
supdoc/html/tags.py
supdoc/lib/__init__.py
supdoc/lib/log.py
supdoc/lib/memo.py
supdoc/lib/path.py
supdoc/lib/py.py
supdoc/lib/text.py
supdoc/lib/itr/__init__.py
supdoc/lib/itr/recipes.py
supdoc/lib/terminal/__init__.py
supdoc/lib/terminal/ansi.py
supdoc/lib/terminal/box.py
supdoc/lib/terminal/html.py
supdoc/lib/terminal/printer.py
supdoc/lib/terminal/tty.py