Metadata-Version: 2.1
Name: supdoc
Version: 0.1.1
Summary: inspection-based documentation tool
Home-page: https://github.com/alexhsamuel/supdoc
Author: Alex Samuel
Author-email: alex@alexsamuel.net
License: MIT
Keywords: documentation,docs
Platform: UNKNOWN
Classifier: Intended Audience :: Developers
Classifier: License :: OSI Approved :: MIT License
Classifier: Programming Language :: Python :: 3
Classifier: Programming Language :: Python :: 3.6
Classifier: Programming Language :: Python :: 3.7
Classifier: Programming Language :: Python :: 3.8
Requires-Python: >=3.6
